LICENSE.txt
MANIFEST.in
mysql2json.py
setup.py
mysql2xxxx.egg-info/PKG-INFO
mysql2xxxx.egg-info/SOURCES.txt
mysql2xxxx.egg-info/dependency_links.txt
mysql2xxxx.egg-info/requires.txt
mysql2xxxx.egg-info/top_level.txt