Metadata-Version: 1.1
Name: mysql2xxxx
Version: 0.1
Summary: Includes the script mysql2json for getting JSON from a MySQL database
Home-page: https://github.com/Flimm/mysql2xxxx-python
Author: David D Lowe
Author-email: daviddlowe.flimm@gmail.com
License: UNKNOWN
Platform: UNKNOWN
Classifier: Development Status :: 2 - Pre-Alpha
Classifier: Programming Language :: Python :: 3
Classifier: License :: OSI Approved :: MIT License
